AUTHORS
COPYING
LICENSE
MANIFEST.in
README
chipsec-manual.pdf
chipsec_main.py
chipsec_util.py
setup.py
chipsec/VERSION
chipsec/WARNING.txt
chipsec/__init__.py
chipsec/chipset.py
chipsec/command.py
chipsec/config.py
chipsec/module.py
chipsec/module_common.py
chipsec/parsers.py
chipsec/testcase.py
chipsec.egg-info/PKG-INFO
chipsec.egg-info/SOURCES.txt
chipsec.egg-info/dependency_links.txt
chipsec.egg-info/entry_points.txt
chipsec.egg-info/top_level.txt
chipsec/cfg/__init__.py
chipsec/cfg/chipsec_cfg.xsd
chipsec/cfg/template.xml
chipsec/cfg/1022/common.xml
chipsec/cfg/1022/renoir.xml
chipsec/cfg/1022/strix.xml
chipsec/cfg/8086/adl.xml
chipsec/cfg/8086/apl.xml
chipsec/cfg/8086/avn.xml
chipsec/cfg/8086/bdw.xml
chipsec/cfg/8086/bdx.xml
chipsec/cfg/8086/byt.xml
chipsec/cfg/8086/cfl.xml
chipsec/cfg/8086/cht.xml
chipsec/cfg/8086/cml.xml
chipsec/cfg/8086/common.xml
chipsec/cfg/8086/dnv.xml
chipsec/cfg/8086/ehl.xml
chipsec/cfg/8086/glk.xml
chipsec/cfg/8086/hsw.xml
chipsec/cfg/8086/hsx.xml
chipsec/cfg/8086/icl.xml
chipsec/cfg/8086/icx.xml
chipsec/cfg/8086/iommu.xml
chipsec/cfg/8086/ivb.xml
chipsec/cfg/8086/ivt.xml
chipsec/cfg/8086/jkt.xml
chipsec/cfg/8086/kbl.xml
chipsec/cfg/8086/mtl.xml
chipsec/cfg/8086/pch_1xx.xml
chipsec/cfg/8086/pch_2xx.xml
chipsec/cfg/8086/pch_3xx.xml
chipsec/cfg/8086/pch_3xxlp.xml
chipsec/cfg/8086/pch_3xxop.xml
chipsec/cfg/8086/pch_495.xml
chipsec/cfg/8086/pch_4xx.xml
chipsec/cfg/8086/pch_4xxh.xml
chipsec/cfg/8086/pch_4xxlp.xml
chipsec/cfg/8086/pch_5xxh.xml
chipsec/cfg/8086/pch_5xxlp.xml
chipsec/cfg/8086/pch_6xxP.xml
chipsec/cfg/8086/pch_6xxS.xml
chipsec/cfg/8086/pch_7x.xml
chipsec/cfg/8086/pch_8x.xml
chipsec/cfg/8086/pch_c60x.xml
chipsec/cfg/8086/pch_c61x.xml
chipsec/cfg/8086/pch_c620.xml
chipsec/cfg/8086/pmc_i440fx.xml
chipsec/cfg/8086/qrk.xml
chipsec/cfg/8086/rkl.xml
chipsec/cfg/8086/rpl.xml
chipsec/cfg/8086/sfdp.xml
chipsec/cfg/8086/skl.xml
chipsec/cfg/8086/skx.xml
chipsec/cfg/8086/snb.xml
chipsec/cfg/8086/tglh.xml
chipsec/cfg/8086/tglu.xml
chipsec/cfg/8086/tpm12.xml
chipsec/cfg/8086/txt.xml
chipsec/cfg/8086/whl.xml
chipsec/cfg/parsers/__init__.py
chipsec/cfg/parsers/core_parsers.py
