Metadata-Version: 2.1
Name: chipsec
Version: 1.13.16
Summary: CHIPSEC: Platform Security Assessment Framework
Home-page: https://github.com/chipsec/chipsec
Download-URL: https://github.com/chipsec/chipsec
Author: CHIPSEC Team
Author-email: chipsec@intel.com
License: GNU General Public License v2 (GPLv2)
Platform: any
Classifier: Development Status :: 5 - Production/Stable
Classifier: Environment :: Console
Classifier: License :: OSI Approved :: GNU General Public License v2 (GPLv2)
Classifier: Natural Language :: English
Classifier: Operating System :: Microsoft :: Windows
Classifier: Operating System :: POSIX :: Linux
Classifier: Operating System :: MacOS :: MacOS X
Classifier: Programming Language :: Python :: 3
Classifier: Programming Language :: Python :: 3.6
Classifier: Topic :: Security
Classifier: Topic :: System :: Hardware
License-File: LICENSE
License-File: COPYING
License-File: AUTHORS
